AUTHORS.rst
CONTRIBUTING.rst
HISTORY.rst
LICENSE
MANIFEST.in
README.rst
setup.cfg
setup.py
django_multipleformwizard.egg-info/PKG-INFO
django_multipleformwizard.egg-info/SOURCES.txt
django_multipleformwizard.egg-info/dependency_links.txt
django_multipleformwizard.egg-info/not-zip-safe
django_multipleformwizard.egg-info/requires.txt
django_multipleformwizard.egg-info/top_level.txt
multipleformwizard/__init__.py
multipleformwizard/views.py
multipleformwizard/templates/multipleformwizard/wizard_form.html