Metadata-Version: 1.1
Name: django-multipleformwizard
Version: 0.2.13
Summary: An extension to the official Django form wizard supporting multiple forms on a wizard step.
Home-page: https://github.com/vikingco/django-multipleformwizard
Author: Dirk Moors
Author-email: dirkmoors@gmail.com
License: MIT
Keywords: django multipleformwizard multiple form wizard
Platform: UNKNOWN
Classifier: Development Status :: 4 - Beta
Classifier: Framework :: Django
Classifier: Intended Audience :: Developers
Classifier: License :: OSI Approved :: MIT License
Classifier: Natural Language :: English
Classifier: Programming Language :: Python :: 2
Classifier: Programming Language :: Python :: 2.7
Classifier: Programming Language :: Python :: 3
Classifier: Programming Language :: Python :: 3.3
